terrascript_aws/__init__.py
terrascript_aws/accessanalyzer/__init__.py
terrascript_aws/accessanalyzer/analyzer.py
terrascript_aws/accessanalyzer/archive_rule.py
terrascript_aws/account/__init__.py
terrascript_aws/account/alternate_contact.py
terrascript_aws/acm/__init__.py
terrascript_aws/acm/certificate.py
terrascript_aws/acm/certificate_validation.py
terrascript_aws/acm/ds_certificate.py
terrascript_aws/acmpca/__init__.py
terrascript_aws/acmpca/certificate.py
terrascript_aws/acmpca/certificate_authority.py
terrascript_aws/acmpca/certificate_authority_certificate.py
terrascript_aws/acmpca/ds_certificate.py
terrascript_aws/acmpca/ds_certificate_authority.py
terrascript_aws/acmpca/permission.py
terrascript_aws/acmpca/policy.py
terrascript_aws/amp/__init__.py
terrascript_aws/amp/ds_prometheus_workspace.py
terrascript_aws/amp/prometheus_alert_manager_definition.py
terrascript_aws/amp/prometheus_rule_group_namespace.py
terrascript_aws/amp/prometheus_workspace.py
terrascript_aws/amplify/__init__.py
terrascript_aws/amplify/app.py
terrascript_aws/amplify/backend_environment.py
terrascript_aws/amplify/branch.py
terrascript_aws/amplify/domain_association.py
terrascript_aws/amplify/webhook.py
terrascript_aws/api_gateway/__init__.py
terrascript_aws/api_gateway/account.py
terrascript_aws/api_gateway/api_key.py
terrascript_aws/api_gateway/authorizer.py
terrascript_aws/api_gateway/base_path_mapping.py
terrascript_aws/api_gateway/client_certificate.py
terrascript_aws/api_gateway/deployment.py
terrascript_aws/api_gateway/documentation_part.py
terrascript_aws/api_gateway/documentation_version.py
terrascript_aws/api_gateway/domain_name.py
terrascript_aws/api_gateway/ds_api_key.py
terrascript_aws/api_gateway/ds_domain_name.py
terrascript_aws/api_gateway/ds_export.py
terrascript_aws/api_gateway/ds_resource.py
terrascript_aws/api_gateway/ds_rest_api.py
terrascript_aws/api_gateway/ds_sdk.py
terrascript_aws/api_gateway/ds_vpc_link.py
terrascript_aws/api_gateway/gateway_response.py
terrascript_aws-1.0.5.dist-info/METADATA
terrascript_aws-1.0.5.dist-info/WHEEL
terrascript_aws-1.0.5.dist-info/RECORD
